{"routes": [{"distanceMeters": 39818, "duration": "1815s", "polyline": {"encodedPolyline": "wrpoEj}bqUqC{C^s@dN}Sr@iAwLmMCWGMsAqAHa@vA{BLa@Hq@C]E]E{@Dm@Xq@FSt@uAFi@rHiLvRaZlBaChBcBdCkB~BqAzWsMdC_BbCqBzB{B|AqB`BiC|AyChAoCfAiDZoA|@yD~@mDd@sAlAoCrAyB|AoBbB_BlCcB`Bw@xBu@vCm@vSwDxIiAxH_AnCo@bLcDxH}A`HsAbSyDhg@oJjPaDlEmAbEyAnQuHpHaDlMwFdAo@hByAjAqAhA}AlEgHbEaHxCgGpBmE|M{\\~AeDrA}BxHyLr@oAdGkJjA{AhBkBxBgB`L}GbCiBzWiWrKiKj@e@vKqKbCsCdCoDxBsD~HiO`BiD~C_GfGmJf@w@hAuBx@iBd@qAf@oB|CqOt@uC`AmCdA_CrA{BlBgCvBuBvBaBfBeAbBs@zA_@zAUvBIrDH`GPfBAjBMdB[~Ac@rB{@tOsIpAi@xAg@hB_@pBSjLUdCOdEg@~Be@tEgARIlM{ClB]PGtCWtEO|^e@rE@nDPpD^pCf@xD`AnC~@`DtAfGlDpVtNpB`ApBn@fIhBbFvAnBp@REvGnBt@Lz@Bt@It@Un@[xC}BBS`EuDLUhE}Dj@w@t@qA`@mA`@iBNeBVaNHiAL[ZoCfAsFz@cEXyBPyBD}CCyBKoBa@kEOkAuDab@_@yCmKgq@[}CO{CE_DAyOKyDU}Ca@yCW{A{@kD}@{CqAgDwB{Fu@iCo@aDm@gFUcDs@uK]iEuCo[mBmTSiFQsSMsYHgFJaCZgEd@mDx@qEh@yB`AcDnAeDxC}G`AsCh@qBz@_E\\iCTiDHyBDaDMwk@Ied@]izAIyIO{EYsEe@wE_Jgo@a@sES{EC{DRoWC}BO{C]wCiLut@oAiG}AgGsE_Qm@sCa@wCiAiNmAmPO{DEyE?a]@uWFaDVeEbB_QVSrAmINe@`@i@vEoD{EgK{CuGOSMOg@y@e[oa@iCeDG[U_@yEiGOPsAl@y@NwKAwHG[KeE?iNAgBAqPEOJuOC}CJ}BNkLl@aDS[AsDWEO_Ku@mAEwFB"}}]}