{"routes": [{"distanceMeters": 33629, "duration": "1467s", "polyline": {"encodedPolyline": "i_unEzsxpUqEzLmBgAq@m@qAcB]]}GiFkB`Jy@fDBh@oA`DaOp[oBlD{GzKkA`CcAlCw@nC[vAOfBKxC?jBp@vTZvEl@xFpB~OZxDPzDFjDg@~iBC^?tKIhXFbPTbLN~D?b@r@lLlFds@ThF|A`|@LdLj@x[HfAfBbbA`@bSNdKAxEMtE[~Ee@rEyD|YsGfg@_AfHUxCEx@ArCHdCVlCJ`Ap@hDr@zBz@hBpPr\\tGxMrHjO`AfCt@lCj@rCZdCPpCHzCC~CmEtgAYzCe@zCcAdEoB~Hg@vC[vCO`DCxBB`g@Hlf@LrHK`@L~HAzAM|AU~A_@tAc@lAqA~Be@z@Cb@{BhDyAfB_BvAaC~Aw@`@mEbByFrByCtAyBpAgAx@oJvHki@pc@mCjBqBjA_Bn@_EhAiFlA_DhAoB|@aCtAuCvBuLvJmUtPqX|Tug@|b@cGvE}VpQ}G~EsCdCeIzHaChBeCzAcChAgC|@wCr@aBX{CZaa@xCyHt@gIp@}Ht@uAT{A`@iAb@aGvCgBn@iB^}ALuBBiBIaBWoHyAiBQmBEiBHmBVkBf@iBt@mCbBkXrQwAr@uBp@cBXgBL}@?o^eAiBQeB_@aBm@}Ay@kF{Dmd@i]oBoA_CiAqBu@gD{@}m@iNiDc@}CQuCCwCJcHb@{CDcCCuCOoDc@cDq@mH{BeEaB}JiEa@o@{C{AaA]eB_@c@QIODWJUx@R`AJnD@b@BdA\\d@Vp@j@f@v@|ApElBdGp@bBl@v@bHnEk@~A_@xAILMBiCH[HURMXCd@D^Pj@Zb@\\PdALj@R`@^\\t@j@tBTbB"}}]}