{"routes": [{"distanceMeters": 23084, "duration": "1494s", "polyline": {"encodedPolyline": "}sumEl{ypUD~DBbDP`TJhCZfCVpAf@hB`ElLhL|\\lCbI~AjFzBpGvBfGPXz@hCpEjMAVxAlE_D?[\\WpI?dCRh@?xb@@lD?rt@I~DYxFUdCk@nEm@vDqQl|@eEnSaL`j@oD|Py@rC}@bCkA`C}AjCoA`BsBxBuBfBwObKe^fUiAz@sFlD{DvCwCjCyC`DeC`DkJtNkdAx_BuAfBeAbAsAdAsBhAeBn@qBd@a@@oBP_BDmyAAeEMeE]sU_D{T_DuFe@yEMcX@cADsUAqa@?c_@CuTHeA@WUgE?oBIkDDeAJkAXeDlAwB\\QFkAHyHL_MEw@@q@AoLq@yCOkCD}BTmBb@eK|C}Bb@aBLoCBaH?OFoAE`@_CJcAD_ACoAGiA_BqRcMqO[]GQGyDSgJCiJeBuB_@k@Kg@A}AeC{ImBKuCaJm@yAiAyDgBoFuCsIaDwJSg@yDyLyMia@yCf@kJ?"}}]}