{"routes": [{"distanceMeters": 37298, "duration": "2411s", "polyline": {"encodedPolyline": "eploEbbzqUmKBs_@?]cKIyAUQCmDK{CYeDuCoT[iEGsCJcdBFwBNwBVsB\\eBj@uBfEsKp@_Cd@gCZuCJeC@{F?gV@sSB_BAw^?mCKQ?uIAs@HqBN_BZ{AvDkNB[VmATkBNcERqMA}D_@qOW_IS_JE{IFcIt@{b@?oGMkH]aHc@_GeBuQY{FG_DAyFBsBX_G`B{UZ}CdAgHhAkHT{BLiC@yBEwBUuCcAgIsC}UkGci@QwCC}BF}BN}BlA_NHqC?uBC_AU_DaIki@YaCUsDEuBB}DLyCJqA`@eEVcDtBsVRyDDqBAgB@wJHyBR}A`@uBb@wAl@wAfGgMVI|AuCf@sA\\yAh@yDr@sF`@cBh@uA|@_Bh@w@Di@fAaAlCcB`Bw@xBu@vCm@vSwDxIiAxH_AnCo@bLcDxH}A`HsAbSyDhg@oJjPaDlEmAbEyAnQuHpHaDlMwFdAo@hByAjAqAhA}AlEgHbEaHxCgGpBmE|M{\\~AeDrA}BxHyLr@oAdGkJjA{AhBkBxBgB`L}GbCiBzWiWrKiKj@e@vKqKbCsCdCoDxBsD~HiO`BiD~C_GfGmJf@w@hAuBx@iBd@qAf@oB|CqOt@uC`AmCdA_CrA{BlBgCvBuBvBaBfBeAbBs@zA_@zAUvBIrDH`GPfBAjBMdB[~Ac@rB{@tOsIpAi@xAg@hB_@pBSjLUdCOdEg@~Be@tEgARIvEiARL~GkApAGfA@rANdKlBz@Bv@I`@On@c@^i@\\y@Jq@Bq@CcAy@{JAs@FgAn@iEEWlBeKXmCLiCAiCMeDUiBCa@w@kDuByIe@sCwA_OSsEGcCBiFj@au@GwCS{C]wCi@sCs@kC_CsGsEiM{FsPoAiD}I{Wg@uB]{BQcCCmBBaCbAkQBuBEyBQkB_@uBeAkD_AcC_B}CiDkF_C_FiGwNsNo\\_AaCsHuPgD_Is@}Bk@mCUoBO_CEsIO_h@RQHkCBmCA}@Fm@LMTCtA?RJL\\Af@INQDaRFgA@S_o@"}}]}