{"routes": [{"distanceMeters": 37501, "duration": "1510s", "polyline": {"encodedPolyline": "ecznExitpUsCSiEg@Gl@DPJJb@LXRJ`@?d@y@lEUp@Af@cI`OuCnF_DzE{EfG{AzAyR`PsAxAgAzA{CxEOJmChE{EtH_AhBmApCgA`D}A|FgLld@yAtEyHhUuDxL{AxDoA~CqA|D_AjDy@rDgHl_@qBjNgCnQyAxMc@nCu@hDy@rCsAfD{E|KcF`NoEzLwA~CkBhD{P~XaBvB}A~A}ArAwClBgQfJuA`AkAhA}@`AgA|AmLdTyAtB_BjBqAnAiBvAcAn@kCvAsS`K{A`AqAjAgApAwA|By@hBw@hCc@xBYtBMzBKjKOfCYxBe@rBi@fB}@pBiXhi@sAvB}AnBsAnAwAbA}Az@cBn@oHfBcLdCeIxA_Dz@qCbAgD~AoCdBoCtByBvBaBjBuNfQQX_BpAsG|DyAjA{ThUgGpGyArB_A`By@pBm@hBg@~Bq@tEaAnGqAnGuB`Jq@tBw@dBkArB{RlZiAxAqAnAkBrAqBfAiDnAkOlF_Bv@oBrAeBbBmA|A_IdMcBrC{@fAeB`BcMbJoSnOmCdBqCzASBqDxAc~@rZiClAcCzAiBvAcBbBaBpBwAzBiQlZ}AtBeBpB_BtA{B`B_CrAgCfAoNpFcCpAoCjBcBtAcCfCwJfMiBfBmBvAeB`A{Ap@{Ad@aB^aCZuWjBaCTqn@hEcC\\cCh@uCbAuPtGuDlA{EjA_wA|VmU~D}BRcD?gCOoBYyBi@qNoE_BYoBQiB@kBP}AZcBl@wAr@aAr@wArAuRxVsC~CEh@_DbDyJ`LaR`SuLlM}e@dh@{NdP{CbD{A~Ao@d@sV~W]JwBfBkBlAcBx@]AkI|CiARqADiBMw@Ss@]{@s@wAuBcA}BECy@mCs@eDoAmHQEw@mDeAeDuAeD{AsCw[if@aFuGqIuKDWeAyAaC{DsBkDGc@D[T]`@c@uBeDgN{Sw\\{g@Oe@y@{AoAiB_KjK{EjFW\\sHfIeGjGO@wMkSiBoC"}}]}